fallback_property/__init__.py
fallback_property-0.2.0.dist-info/LICENSE
fallback_property-0.2.0.dist-info/WHEEL
fallback_property-0.2.0.dist-info/METADATA
fallback_property-0.2.0.dist-info/RECORD
